keybasepy/__init__.py
keybasepy/bot.py
keybasepy/models.py
keybasepy-0.1.3.dist-info/LICENSE.txt
keybasepy-0.1.3.dist-info/WHEEL
keybasepy-0.1.3.dist-info/METADATA
keybasepy-0.1.3.dist-info/RECORD
